{
  "data": {
    "article": {},
    "attachments": {},
    "author_id": "1951181920022437889",
    "conversation_id": "2052796633516245235",
    "created_at": "2026-05-08T17:33:34.000Z",
    "edit_controls": {
      "editable_until": "2026-05-08T18:33:34.000Z",
      "edits_remaining": 5,
      "is_edit_eligible": false
    },
    "edit_history_tweet_ids": [
      "2052804114632040460"
    ],
    "entities": {
      "mentions": [
        {
          "end": 11,
          "id": "1999040656942223360",
          "start": 0,
          "username": "ewan114514"
        }
      ]
    },
    "geo": {},
    "id": "2052804114632040460",
    "in_reply_to_user_id": "1999040656942223360",
    "lang": "zh",
    "note_tweet": {
      "entities": {}
    },
    "possibly_sensitive": false,
    "public_metrics": {
      "bookmark_count": 0,
      "impression_count": 0,
      "like_count": 0,
      "quote_count": 0,
      "reply_count": 0,
      "retweet_count": 0
    },
    "referenced_tweets": [
      {
        "id": "2052796633516245235",
        "type": "replied_to"
      }
    ],
    "reply_settings": "everyone",
    "text": "@ewan114514 天那这简直就是我"
  },
  "includes": {
    "tweets": [
      {
        "article": {},
        "attachments": {},
        "author_id": "1951181920022437889",
        "conversation_id": "2052796633516245235",
        "created_at": "2026-05-08T17:33:34.000Z",
        "edit_controls": {
          "editable_until": "2026-05-08T18:33:34.000Z",
          "edits_remaining": 5,
          "is_edit_eligible": false
        },
        "edit_history_tweet_ids": [
          "2052804114632040460"
        ],
        "entities": {
          "mentions": [
            {
              "end": 11,
              "id": "1999040656942223360",
              "start": 0,
              "username": "ewan114514"
            }
          ]
        },
        "geo": {},
        "id": "2052804114632040460",
        "in_reply_to_user_id": "1999040656942223360",
        "lang": "zh",
        "note_tweet": {
          "entities": {}
        },
        "possibly_sensitive": false,
        "public_metrics": {
          "bookmark_count": 0,
          "impression_count": 0,
          "like_count": 0,
          "quote_count": 0,
          "reply_count": 0,
          "retweet_count": 0
        },
        "referenced_tweets": [
          {
            "id": "2052796633516245235",
            "type": "replied_to"
          }
        ],
        "reply_settings": "everyone",
        "text": "@ewan114514 天那这简直就是我"
      },
      {
        "article": {},
        "attachments": {},
        "author_id": "1999040656942223360",
        "conversation_id": "2052796633516245235",
        "created_at": "2026-05-08T17:03:51.000Z",
        "edit_controls": {
          "editable_until": "2026-05-08T18:03:51.000Z",
          "edits_remaining": 5,
          "is_edit_eligible": true
        },
        "edit_history_tweet_ids": [
          "2052796633516245235"
        ],
        "entities": {
          "urls": [
            {
              "display_url": "x.com/chronic_clinic…",
              "end": 29,
              "expanded_url": "https://twitter.com/chronic_clinic_/status/2052464353111323096",
              "start": 6,
              "url": "https://t.co/aPYZAapdBQ"
            }
          ]
        },
        "geo": {},
        "id": "2052796633516245235",
        "lang": "zh",
        "note_tweet": {
          "entities": {}
        },
        "possibly_sensitive": false,
        "public_metrics": {
          "bookmark_count": 0,
          "impression_count": 22,
          "like_count": 1,
          "quote_count": 0,
          "reply_count": 1,
          "retweet_count": 0
        },
        "referenced_tweets": [
          {
            "id": "2052464353111323096",
            "type": "quoted"
          }
        ],
        "reply_settings": "everyone",
        "text": "有点像推友 https://t.co/aPYZAapdBQ"
      }
    ],
    "users": [
      {
        "created_at": "2025-08-01T07:23:46.000Z",
        "description": "某个神经病的亡魂/超级烟鬼/🟨⬜️🟪⬛️/可以叫我nagi/非三无都会回fo虽然也没人fo（\n没钱抽烟了所以也卖一些烟!vape电子烟常见一次性冰爆鸭嘴兽小黑条70r一件以上包邮还有悦子杆蛋都有! 悦刻注油空蛋9r一个 纸烟有俄产万宝路 查普曼系列 寿百年系列包正!",
        "id": "1951181920022437889",
        "location": "瑞瓦肖,褴褛飞旋",
        "name": "懸想",
        "pinned_tweet_id": "2029813934186975322",
        "profile_image_url": "https://pbs.twimg.com/profile_images/2037140504161218560/uHI5kO5G_normal.jpg",
        "protected": false,
        "public_metrics": {
          "followers_count": 278,
          "following_count": 332,
          "like_count": 2215,
          "listed_count": 0,
          "media_count": 89,
          "tweet_count": 623
        },
        "username": "blackdoginmyhed",
        "verified": false
      },
      {
        "created_at": "2025-12-11T08:57:00.000Z",
        "description": "𝓜𝓮𝓻𝓻𝔂 𝓒𝓱𝓻𝓲𝓼𝓽𝓶𝓪𝓼, 𝓜𝓻. 𝓛𝓪𝔀𝓻𝓮𝓷𝓬𝓮  | choose life",
        "id": "1999040656942223360",
        "location": "第六病室",
        "name": "伊万(absolute",
        "pinned_tweet_id": "2042905392410431801",
        "profile_image_url": "https://pbs.twimg.com/profile_images/2042862844606312448/skmkLiUg_normal.jpg",
        "protected": false,
        "public_metrics": {
          "followers_count": 127,
          "following_count": 155,
          "like_count": 7284,
          "listed_count": 0,
          "media_count": 21,
          "tweet_count": 323
        },
        "username": "ewan114514",
        "verified": false
      }
    ]
  }
}