{
  "data": {
    "article": {},
    "attachments": {},
    "author_id": "1951181920022437889",
    "conversation_id": "2059973200440692994",
    "created_at": "2026-05-28T19:09:15.000Z",
    "edit_controls": {
      "editable_until": "2026-05-28T20:09:15.000Z",
      "edits_remaining": 5,
      "is_edit_eligible": false
    },
    "edit_history_tweet_ids": [
      "2060075948268281960"
    ],
    "entities": {
      "mentions": [
        {
          "end": 11,
          "id": "1892530438125875201",
          "start": 0,
          "username": "adogtwting"
        }
      ]
    },
    "geo": {},
    "id": "2060075948268281960",
    "in_reply_to_user_id": "1892530438125875201",
    "lang": "in",
    "note_tweet": {
      "entities": {}
    },
    "possibly_sensitive": false,
    "public_metrics": {
      "bookmark_count": 0,
      "impression_count": 0,
      "like_count": 0,
      "quote_count": 0,
      "reply_count": 0,
      "retweet_count": 0
    },
    "referenced_tweets": [
      {
        "id": "2059973200440692994",
        "type": "replied_to"
      }
    ],
    "reply_settings": "everyone",
    "text": "@adogtwting pspspspsps"
  },
  "includes": {
    "tweets": [
      {
        "article": {},
        "attachments": {},
        "author_id": "1951181920022437889",
        "conversation_id": "2059973200440692994",
        "created_at": "2026-05-28T19:09:15.000Z",
        "edit_controls": {
          "editable_until": "2026-05-28T20:09:15.000Z",
          "edits_remaining": 5,
          "is_edit_eligible": false
        },
        "edit_history_tweet_ids": [
          "2060075948268281960"
        ],
        "entities": {
          "mentions": [
            {
              "end": 11,
              "id": "1892530438125875201",
              "start": 0,
              "username": "adogtwting"
            }
          ]
        },
        "geo": {},
        "id": "2060075948268281960",
        "in_reply_to_user_id": "1892530438125875201",
        "lang": "in",
        "note_tweet": {
          "entities": {}
        },
        "possibly_sensitive": false,
        "public_metrics": {
          "bookmark_count": 0,
          "impression_count": 0,
          "like_count": 0,
          "quote_count": 0,
          "reply_count": 0,
          "retweet_count": 0
        },
        "referenced_tweets": [
          {
            "id": "2059973200440692994",
            "type": "replied_to"
          }
        ],
        "reply_settings": "everyone",
        "text": "@adogtwting pspspspsps"
      },
      {
        "article": {},
        "attachments": {},
        "author_id": "1892530438125875201",
        "conversation_id": "2059973200440692994",
        "created_at": "2026-05-28T12:20:58.000Z",
        "edit_controls": {
          "editable_until": "2026-05-28T13:20:58.000Z",
          "edits_remaining": 5,
          "is_edit_eligible": true
        },
        "edit_history_tweet_ids": [
          "2059973200440692994"
        ],
        "entities": {},
        "geo": {},
        "id": "2059973200440692994",
        "lang": "nl",
        "note_tweet": {
          "entities": {}
        },
        "possibly_sensitive": false,
        "public_metrics": {
          "bookmark_count": 6,
          "impression_count": 6654,
          "like_count": 297,
          "quote_count": 10,
          "reply_count": 36,
          "retweet_count": 53
        },
        "reply_settings": "everyone",
        "text": "woof woof woof woof woof woof woof"
      }
    ],
    "users": [
      {
        "created_at": "2025-08-01T07:23:46.000Z",
        "description": "某个神经病的亡魂/超级烟鬼肺癌预备役/🟨⬜️🟪⬛️/代词随意/可以叫我nagi/日常碎碎念推以及神必小测评/没回fo私聊喊我\n没钱抽烟了赚点钱买烟!电子🚬常见一次性冰爆鸭嘴兽小黑条70r一件以上包邮还有悦子杆蛋啥乱七八糟的都有! 悦刻注油空蛋9r一个 🚬均俄产 万宝路查普曼寿百年系列还有卡比龙!包正!",
        "id": "1951181920022437889",
        "location": "瑞瓦肖,褴褛飞旋",
        "name": "懸想",
        "pinned_tweet_id": "2029813934186975322",
        "profile_image_url": "https://pbs.twimg.com/profile_images/2037140504161218560/uHI5kO5G_normal.jpg",
        "protected": false,
        "public_metrics": {
          "followers_count": 465,
          "following_count": 541,
          "like_count": 3490,
          "listed_count": 0,
          "media_count": 130,
          "tweet_count": 1024
        },
        "username": "blackdoginmyhed",
        "verified": false
      },
      {
        "created_at": "2025-02-20T11:03:19.000Z",
        "description": "literally just a dog with a blog",
        "id": "1892530438125875201",
        "location": "dog park",
        "name": "dog",
        "pinned_tweet_id": "2060073732308111493",
        "profile_image_url": "https://pbs.twimg.com/profile_images/2050344276744159232/d2wBHGv8_normal.jpg",
        "protected": false,
        "public_metrics": {
          "followers_count": 11982,
          "following_count": 126,
          "like_count": 183,
          "listed_count": 40,
          "media_count": 68,
          "tweet_count": 344
        },
        "username": "adogtwting",
        "verified": true
      }
    ]
  }
}