{
  "data": {
    "article": {},
    "attachments": {},
    "author_id": "1951181920022437889",
    "conversation_id": "2040470965394739606",
    "created_at": "2026-04-04T18:15:45.000Z",
    "edit_controls": {
      "editable_until": "2026-04-04T19:15:45.000Z",
      "edits_remaining": 5,
      "is_edit_eligible": false
    },
    "edit_history_tweet_ids": [
      "2040493540510421292"
    ],
    "entities": {
      "mentions": [
        {
          "end": 16,
          "id": "1563508655256850433",
          "start": 0,
          "username": "Starrynightwglf"
        }
      ]
    },
    "geo": {},
    "id": "2040493540510421292",
    "in_reply_to_user_id": "1563508655256850433",
    "lang": "und",
    "note_tweet": {
      "entities": {}
    },
    "possibly_sensitive": false,
    "public_metrics": {
      "bookmark_count": 0,
      "impression_count": 0,
      "like_count": 0,
      "quote_count": 0,
      "reply_count": 0,
      "retweet_count": 0
    },
    "referenced_tweets": [
      {
        "id": "2040470965394739606",
        "type": "replied_to"
      }
    ],
    "reply_settings": "everyone",
    "text": "@Starrynightwglf (　^ω^)"
  },
  "includes": {
    "media": [
      {
        "height": 3640,
        "media_key": "3_2040470950240714753",
        "public_metrics": {},
        "type": "photo",
        "url": "https://pbs.twimg.com/media/HFE1hLOaAAEj06p.jpg",
        "width": 1200
      },
      {
        "height": 3102,
        "media_key": "3_2040470950228135936",
        "public_metrics": {},
        "type": "photo",
        "url": "https://pbs.twimg.com/media/HFE1hLLaEAA0XJu.jpg",
        "width": 1200
      },
      {
        "height": 3573,
        "media_key": "3_2040470950555328512",
        "public_metrics": {},
        "type": "photo",
        "url": "https://pbs.twimg.com/media/HFE1hMZaoAAsUCb.jpg",
        "width": 1200
      },
      {
        "height": 2692,
        "media_key": "3_2040470950546939904",
        "public_metrics": {},
        "type": "photo",
        "url": "https://pbs.twimg.com/media/HFE1hMXaoAAzvay.jpg",
        "width": 1200
      }
    ],
    "tweets": [
      {
        "article": {},
        "attachments": {},
        "author_id": "1951181920022437889",
        "conversation_id": "2040470965394739606",
        "created_at": "2026-04-04T18:15:45.000Z",
        "edit_controls": {
          "editable_until": "2026-04-04T19:15:45.000Z",
          "edits_remaining": 5,
          "is_edit_eligible": false
        },
        "edit_history_tweet_ids": [
          "2040493540510421292"
        ],
        "entities": {
          "mentions": [
            {
              "end": 16,
              "id": "1563508655256850433",
              "start": 0,
              "username": "Starrynightwglf"
            }
          ]
        },
        "geo": {},
        "id": "2040493540510421292",
        "in_reply_to_user_id": "1563508655256850433",
        "lang": "und",
        "note_tweet": {
          "entities": {}
        },
        "possibly_sensitive": false,
        "public_metrics": {
          "bookmark_count": 0,
          "impression_count": 0,
          "like_count": 0,
          "quote_count": 0,
          "reply_count": 0,
          "retweet_count": 0
        },
        "referenced_tweets": [
          {
            "id": "2040470965394739606",
            "type": "replied_to"
          }
        ],
        "reply_settings": "everyone",
        "text": "@Starrynightwglf (　^ω^)"
      },
      {
        "article": {},
        "attachments": {
          "media_keys": [
            "3_2040470950240714753",
            "3_2040470950228135936",
            "3_2040470950555328512",
            "3_2040470950546939904"
          ]
        },
        "author_id": "1563508655256850433",
        "conversation_id": "2040470965394739606",
        "created_at": "2026-04-04T16:46:02.000Z",
        "edit_controls": {
          "editable_until": "2026-04-04T17:46:02.000Z",
          "edits_remaining": 5,
          "is_edit_eligible": true
        },
        "edit_history_tweet_ids": [
          "2040470965394739606"
        ],
        "entities": {
          "urls": [
            {
              "display_url": "pic.x.com/4CuvXLiWwX",
              "end": 130,
              "expanded_url": "https://x.com/Starrynightwglf/status/2040470965394739606/photo/1",
              "media_key": "3_2040470950240714753",
              "start": 107,
              "url": "https://t.co/4CuvXLiWwX"
            },
            {
              "display_url": "pic.x.com/4CuvXLiWwX",
              "end": 130,
              "expanded_url": "https://x.com/Starrynightwglf/status/2040470965394739606/photo/1",
              "media_key": "3_2040470950228135936",
              "start": 107,
              "url": "https://t.co/4CuvXLiWwX"
            },
            {
              "display_url": "pic.x.com/4CuvXLiWwX",
              "end": 130,
              "expanded_url": "https://x.com/Starrynightwglf/status/2040470965394739606/photo/1",
              "media_key": "3_2040470950555328512",
              "start": 107,
              "url": "https://t.co/4CuvXLiWwX"
            },
            {
              "display_url": "pic.x.com/4CuvXLiWwX",
              "end": 130,
              "expanded_url": "https://x.com/Starrynightwglf/status/2040470965394739606/photo/1",
              "media_key": "3_2040470950546939904",
              "start": 107,
              "url": "https://t.co/4CuvXLiWwX"
            }
          ]
        },
        "geo": {},
        "id": "2040470965394739606",
        "lang": "ja",
        "note_tweet": {
          "entities": {}
        },
        "possibly_sensitive": false,
        "public_metrics": {
          "bookmark_count": 5,
          "impression_count": 1405,
          "like_count": 27,
          "quote_count": 0,
          "reply_count": 7,
          "retweet_count": 0
        },
        "reply_settings": "everyone",
        "text": "好久没上岛了在女装版看到了....\n没有RLE、没有HRT（疑似）、没有炸柜（术后才炸）、还未毕业的mtf，在泰国直接开证手术，然后过司法鉴定了，现在在版上问住女生宿舍怎么女装不被当男的\n信息量有点大(°ー°〃) https://t.co/4CuvXLiWwX"
      }
    ],
    "users": [
      {
        "created_at": "2025-08-01T07:23:46.000Z",
        "description": "某个神经病的亡魂/🟨⬜️🟪⬛️/可以叫我nagi/非三无都会回fo虽然也没人fo（\n没钱抽烟了所以也卖一些电子烟!常见一次性冰爆鸭嘴兽小黑条还有杆蛋都有!",
        "id": "1951181920022437889",
        "location": "瑞瓦肖,褴褛飞旋",
        "name": "懸想",
        "pinned_tweet_id": "2029813934186975322",
        "profile_image_url": "https://pbs.twimg.com/profile_images/2037140504161218560/uHI5kO5G_normal.jpg",
        "protected": false,
        "public_metrics": {
          "followers_count": 94,
          "following_count": 152,
          "like_count": 967,
          "listed_count": 0,
          "media_count": 54,
          "tweet_count": 294
        },
        "username": "blackdoginmyhed",
        "verified": false
      },
      {
        "created_at": "2022-08-27T12:48:14.000Z",
        "description": "风起 风声是你在哭泣\nㅤㅤㅤㅤㅤㅤㅤㅤㅤ🚪52",
        "id": "1563508655256850433",
        "location": "ㅤ",
        "name": "风🎐",
        "pinned_tweet_id": "2001381216176750880",
        "profile_image_url": "https://pbs.twimg.com/profile_images/1898934186553352192/j3riaQGy_normal.jpg",
        "protected": false,
        "public_metrics": {
          "followers_count": 1944,
          "following_count": 4435,
          "like_count": 150867,
          "listed_count": 3,
          "media_count": 1293,
          "tweet_count": 5887
        },
        "username": "Starrynightwglf",
        "verified": false
      }
    ]
  }
}